app_users/__init__.py
app_users/admin.py
app_users/apps.py
app_users/forms.py
app_users/models.py
app_users/serializers.py
app_users/tests.py
app_users/urls.py
app_users/views.py
app_users/migrations/0001_initial.py
app_users/migrations/__init__.py
customusers-1.0.3.dist-info/METADATA
customusers-1.0.3.dist-info/WHEEL
customusers-1.0.3.dist-info/top_level.txt
customusers-1.0.3.dist-info/RECORD
