Metadata-Version: 2.1
Name: customusers
Version: 1.0.3
Summary: A simple Django app to create custom users and their RESTful APIs.
Home-page: UNKNOWN
Author: Kenneth Mathenge
Author-email: mathenge@example.com
License: UNKNOWN
Platform: UNKNOWN
Classifier: Environment :: Web Environment
Classifier: Framework :: Django
Classifier: Intended Audience :: Developers
Classifier: Operating System :: OS Independent
Classifier: Programming Language :: Python
Classifier: Programming Language :: Python :: 3.6
Classifier: Topic :: Internet :: WWW/HTTP
Classifier: Topic :: Internet :: WWW/HTTP :: Dynamic Content
